py2dag/__init__.py
py2dag/cli.py
py2dag/colors.py
py2dag/export_dagre.py
py2dag/export_svg.py
py2dag/parser.py
py2dag/pseudo.py
py2dag-0.3.22.dist-info/METADATA
py2dag-0.3.22.dist-info/WHEEL
py2dag-0.3.22.dist-info/entry_points.txt
py2dag-0.3.22.dist-info/licenses/LICENSE
py2dag-0.3.22.dist-info/RECORD
