Metadata-Version: 2.4
Name: py2dag
Version: 0.3.22
Summary: Convert Python function plans to DAG (JSON, pseudo, optional SVG).
License: MIT
License-File: LICENSE
Author: rvergis
Requires-Python: >=3.8,<4.0
Classifier: License :: OSI Approved :: MIT License
Classifier: Programming Language :: Python :: 3
Classifier: Programming Language :: Python :: 3.8
Classifier: Programming Language :: Python :: 3.9
Classifier: Programming Language :: Python :: 3.10
Classifier: Programming Language :: Python :: 3.11
Classifier: Programming Language :: Python :: 3.12
Classifier: Programming Language :: Python :: 3.13
Classifier: Programming Language :: Python :: 3.14
Provides-Extra: svg
Requires-Dist: graphviz (>=0.20.3,<0.21.0) ; extra == "svg"
